AUTHORS
LICENCE
MANIFEST.in
README.rst
requirements.txt
setup.py
Freezes.egg-info/PKG-INFO
Freezes.egg-info/SOURCES.txt
Freezes.egg-info/dependency_links.txt
Freezes.egg-info/entry_points.txt
Freezes.egg-info/not-zip-safe
Freezes.egg-info/requires.txt
Freezes.egg-info/top_level.txt
freezes/__init__.py
freezes/__main__.py
freezes/_assets.yml
freezes/_config.yml
freezes/babel.cfg
freezes/config.py
freezes/mapaths.json
freezes/pagext.py
freezes/scripts.py
freezes/server.py
freezes/sites.py
freezes/views.py
freezes/layouts/404.html
freezes/layouts/archived.html
freezes/layouts/archives.html
freezes/layouts/page.html
freezes/layouts/post.html
freezes/layouts/recent.html
freezes/layouts/tagged.html
freezes/layouts/tags.html
freezes/seeds/about.md
freezes/seeds/index.md
freezes/static/_scripts/startup.coffee
freezes/static/_styles/elements.less
freezes/static/_styles/errors.less
freezes/static/_styles/pages.less
freezes/static/_styles/posts.less
freezes/static/images/blockquote.png
freezes/templates/base.html
freezes/templates/sitemap.xml
freezes/templates/_includes/_footer.html
freezes/templates/_includes/_header.html
freezes/templates/_includes/_metas.html
freezes/templates/_includes/_navbar.html
freezes/templates/_includes/_post_nav.html
freezes/templates/_includes/_tags.html
freezes/templates/_layouts/_archived.html
freezes/templates/_layouts/_archives.html
freezes/templates/_layouts/_error.html
freezes/templates/_layouts/_page.html
freezes/templates/_layouts/_post.html
freezes/templates/_layouts/_recent.html
freezes/templates/_layouts/_tagged.html
freezes/templates/_layouts/_tags.html
freezes/templates/_macros/disqus.html
freezes/templates/_macros/posts.html
freezes/translations/messages.pot
freezes/translations/zh/LC_MESSAGES/messages.mo
freezes/translations/zh/LC_MESSAGES/messages.po
tests/test_app/__init__.py
tests/test_app/_assets.yml
tests/test_app/_config.yml
tests/test_app/babel.cfg
tests/test_app/static/images/blockquote.png
tests/test_app/static/scripts/startup.coffee
tests/test_app/static/styles/elements.less
tests/test_app/static/styles/errors.less
tests/test_app/static/styles/pages.less
tests/test_app/static/styles/posts.less
tests/test_app/templates/404.html
