Metadata-Version: 1.1
Name: Freezes
Version: 1.0.7
Summary: Transform the plain text or blog to static website
Home-page: http://freezes.dotnetage.com
Author: Ray
Author-email: csharp2002@hotmail.com
License: BSD
Keywords: static,flask
Platform: any
Classifier: Development Status :: 4 - Beta
Classifier: Intended Audience :: Developers
Classifier: License :: OSI Approved :: BSD License
Classifier: Natural Language :: English
Classifier: Operating System :: OS Independent
Classifier: Programming Language :: Python :: 2.6
Classifier: Programming Language :: Python :: 2.7
Classifier: Programming Language :: Python :: 3.2
Classifier: Programming Language :: Python :: 3.3
Classifier: Programming Language :: Python :: 3.4
Classifier: Topic :: Software Development :: Libraries
Classifier: Topic :: Utilities
